radix/__init__.py
radix/_radix.cpython-314-x86_64-linux-musl.so
radix/radix.py
py_radix-1.1.0.dist-info/METADATA
py_radix-1.1.0.dist-info/WHEEL
py_radix-1.1.0.dist-info/top_level.txt
py_radix-1.1.0.dist-info/RECORD
py_radix-1.1.0.dist-info/licenses/LICENSE
